{
  "version": "v1.2.0",
  "dataSnapshotId": "20251119-214357",
  "pipelineGitSha": "5666b76",
  "containerImageDigest": "dev-local",
  "artifactUri": "gs://rideease-models/v1.2.0/model.json",
  "metrics": {
    "offline": {
      "users": 0,
      "avgNDCG": 0,
      "avgHitRate": 0,
      "low": {
        "ndcg": 0,
        "hit": 0,
        "n": 0
      },
      "high": {
        "ndcg": 0,
        "hit": 0,
        "n": 0
      }
    },
    "evalCutoff": "2025-11-19T02:44:02.265Z",
    "lookbackDays": 30
  },
  "trainedAt": "2025-11-20T02:44:02.266Z"
}